ec2_tag_conditional/__init__.py
ec2_tag_conditional/util.py
ec2_tag_conditional-0.1.2.dist-info/METADATA
ec2_tag_conditional-0.1.2.dist-info/RECORD
ec2_tag_conditional-0.1.2.dist-info/WHEEL
ec2_tag_conditional-0.1.2.dist-info/entry_points.txt
ec2_tag_conditional-0.1.2.dist-info/top_level.txt
